python_cel-0.1.1.dist-info/METADATA
python_cel-0.1.1.dist-info/WHEEL
cel/_cel.pyi
cel/__init__.py
cel/py.typed
cel/_cel.abi3.so
python_cel-0.1.1.dist-info/RECORD
