Metadata-Version: 2.4
Name: python-cel
Version: 0.1.1
Classifier: Programming Language :: Rust
Classifier: Programming Language :: Python :: Implementation :: CPython
Classifier: Programming Language :: Python :: Implementation :: PyPy
Summary: Python bindings for the cel-rust crate
Author-email: Tim Pogue <tim@emergentmethods.ai>
License: MIT
Requires-Python: >=3.10, <4.0
Project-URL: repository, https://gitlab.com/emergentmethods/python-cel
